{
  "id": "prop-e056d996",
  "op": "create",
  "module": "knowledge",
  "target": "failing-tool-read",
  "change": {
    "type": "knowledge",
    "title": "Read fails frequently",
    "body": "Tool `Read` fails frequently in this project (42 failures observed) — worth investigating why."
  },
  "rationale": "Tool `Read` fails frequently in this project (42 failures observed) — worth investigating why.",
  "evidence": [
    {
      "kind": "fact",
      "occurrences": 42
    }
  ],
  "confidence": null,
  "score": 42,
  "status": "pending"
}
